{
	"positionDefinitions": [
		{
			"name": "afa59d6a",
			"positions": [
				{
					"x": 0.0,
					"y": 0.0,
					"z": 40.0
				},
				{
					"x": 0.0,
					"y": 0.0,
					"z": -40.0
				}
			],
			"positionsFlipped": [
				{
					"x": 0.0,
					"y": 0.0,
					"z": 40.0
				},
				{
					"x": 0.0,
					"y": 0.0,
					"z": -40.0
				}
			]
		},
		{
			"name": "807e13e",
			"positions": [
				{
					"x": 0.0,
					"y": 0.0,
					"z": 0.0
				},
				{
					"x": 0.0,
					"y": 0.0,
					"z": 80.0
				},
				{
					"x": 0.0,
					"y": 0.0,
					"z": -80.0
				}
			],
			"positionsFlipped": [
				{
					"x": 0.0,
					"y": 0.0,
					"z": 0.0
				},
				{
					"x": 0.0,
					"y": 0.0,
					"z": 80.0
				},
				{
					"x": 0.0,
					"y": 0.0,
					"z": -80.0
				}
			]
		},
		{
			"name": "43f0f6d4",
			"positions": [
				{
					"x": 0.0,
					"y": 0.0,
					"z": 106.6
				},
				{
					"x": 0.0,
					"y": 0.0,
					"z": -105.4
				}
			],
			"positionsFlipped": [
				{
					"x": 0.0,
					"y": 0.0,
					"z": 105.4
				},
				{
					"x": 0.0,
					"y": 0.0,
					"z": -106.6
				}
			]
		}
	]
}