{
	"vehicles": [
		{
			"id": "sp1900_normal",
			"name": "train.mtr.sp1900",
			"color": "003399",
			"transportMode": "TRAIN",
			"length": 25,
			"width": 2,
			"bogie1Position": -8.5,
			"bogie2Position": 8.5,
			"wikipediaArticle": "SP1900_EMU",
			"models": [
				{
					"modelResource": "mtr:models/vehicle/sp1900.bbmodel",
					"textureResource": "mtr:textures/vehicle/sp1900.png",
					"modelPropertiesResource": "mtr:properties/vehicle/sp1900_normal.json",
					"positionDefinitionsResource": "mtr:properties/definition/sp1900.json"
				}
			],
			"bogie1Models": [
				{
					"modelResource": "mtr:models/vehicle/bogie_1.bbmodel",
					"textureResource": "mtr:textures/vehicle/bogie_1.png",
					"modelPropertiesResource": "mtr:properties/vehicle/bogie_1.json",
					"positionDefinitionsResource": "mtr:properties/definition/origin.json"
				}
			],
			"bogie2Models": [
				{
					"modelResource": "mtr:models/vehicle/bogie_1.bbmodel",
					"textureResource": "mtr:textures/vehicle/bogie_1.png",
					"modelPropertiesResource": "mtr:properties/vehicle/bogie_1.json",
					"positionDefinitionsResource": "mtr:properties/definition/origin.json"
				}
			],
			"speedSoundCount": 120,
			"speedSoundBaseResource": "sp1900"
		}
	],
	"signs": [
	]
}
