{
    "elements": [
        {   "__comment": "Left handrail",
            "from": [ 4.686, 11.314, 13 ],
            "to": [ 19.314, 10.314, 15 ],
			"rotation": { "origin": [ 8, 11.314, 8 ], "axis": "z", "angle": -45 },
            "faces": {
                "up": { "uv": [ 0, 0, 16, 16 ], "texture": "#lhandrail" },
                "down": { "uv": [ 0, 0, 16, 16 ], "texture": "#lhandrail" },
                "north": { "uv": [ 0, 0, 16, 16 ], "texture": "#lhandrail" },
                "south": { "uv": [ 0, 0, 16, 16 ], "texture": "#lhandrail" },
                "east": { "uv": [ 0, 0, 16, 16 ], "texture": "#lhandrail" },
                "west": { "uv": [ 0, 0, 16, 16 ], "texture": "#lhandrail" }
            }
        },
        {
            "from": [ 0, 16, 13 ],
            "to": [ 6.123, 15, 15 ],
			"rotation": { "origin": [ 0, 16, 8 ], "axis": "z", "angle": -22.5 },
            "faces": {
                "up": { "uv": [ 0, 0, 16, 16 ], "texture": "#lhandrail" },
                "down": { "uv": [ 0, 0, 16, 16 ], "texture": "#lhandrail" },
                "north": { "uv": [ 0, 0, 16, 16 ], "texture": "#lhandrail" },
                "south": { "uv": [ 0, 0, 16, 16 ], "texture": "#lhandrail" },
                "east": { "uv": [ 0, 0, 16, 16 ], "texture": "#lhandrail" },
                "west": { "uv": [ 0, 0, 16, 16 ], "texture": "#lhandrail" }
            }
        },
        {   "__comment": "Right handrail",
            "from": [ 4.686, 11.314, 1 ],
            "to": [ 19.314, 10.314, 3 ],
			"rotation": { "origin": [ 8, 11.314, 8 ], "axis": "z", "angle": -45 },
            "faces": {
                "up": { "uv": [ 0, 0, 16, 16 ], "texture": "#rhandrail" },
                "down": { "uv": [ 0, 0, 16, 16 ], "texture": "#rhandrail" },
                "north": { "uv": [ 0, 0, 16, 16 ], "texture": "#rhandrail" },
                "south": { "uv": [ 0, 0, 16, 16 ], "texture": "#rhandrail" },
                "east": { "uv": [ 0, 0, 16, 16 ], "texture": "#rhandrail" },
                "west": { "uv": [ 0, 0, 16, 16 ], "texture": "#rhandrail" }
            }
        },
        {
            "from": [ 0, 16, 1 ],
            "to": [ 6.123, 15, 3 ],
			"rotation": { "origin": [ 0, 16, 8 ], "axis": "z", "angle": -22.5 },
            "faces": {
                "up": { "uv": [ 0, 0, 16, 16 ], "texture": "#rhandrail" },
                "down": { "uv": [ 0, 0, 16, 16 ], "texture": "#rhandrail" },
                "north": { "uv": [ 0, 0, 16, 16 ], "texture": "#rhandrail" },
                "south": { "uv": [ 0, 0, 16, 16 ], "texture": "#rhandrail" },
                "east": { "uv": [ 0, 0, 16, 16 ], "texture": "#rhandrail" },
                "west": { "uv": [ 0, 0, 16, 16 ], "texture": "#rhandrail" }
            }
        }
    ]
}
