{
	"forge_marker": 1,
	"defaults": {
		"textures": {
			"particle": "mtr:items/psd_glass",
			"body": "mtr:blocks/psd_top"
		},
		"model": "mtr:psd_top"
	},
	"variants": {
		"facing": {
			"west": {},
			"north": { "y": 90 },
			"east": { "y": 180 },
			"south": { "y": 270 }
		},
		"side": {
			"left": { "textures": { "body": "mtr:blocks/psd_top_left" } },
			"right": { "textures": { "body": "mtr:blocks/psd_top_right" } },
			"middle": { "textures": { "body": "mtr:blocks/psd_top" } },
			"single": { "textures": { "body": "mtr:blocks/psd_top" } }
		}
	}
}