{
	"textures": {
		"black": "mtr:block/black",
		"particle": "mtr:block/metal"
	},
	"elements": [
		{
			"from": [ 0, 0, 12 ],
			"to": [ 16, 16, 16 ],
			"faces": {
				"north": { "texture": "#particle" },
				"east": { "texture": "#particle", "cullface": "east" },
				"south": { "texture": "#particle", "cullface": "south" },
				"west": { "texture": "#particle", "cullface": "west" },
				"up": { "texture": "#particle", "cullface": "up" },
				"down": { "texture": "#particle", "cullface": "down" }
			}
		},
		{
			"from": [ 3.5, 1.5, 11.95 ],
			"to": [ 16, 5.5, 11.95 ],
			"faces": {
				"north": { "texture": "#black" },
				"east": { "texture": "#black" },
				"south": { "texture": "#black" },
				"west": { "texture": "#black" },
				"up": { "texture": "#black" },
				"down": { "texture": "#black" }
			}
		}
	]
}
