{
	"parts": [
		{
			"names": [
				"head"
			],
			"positionDefinitions": [
				"624ba1ad"
			],
			"condition": "NORMAL",
			"renderStage": "INTERIOR",
			"type": "NORMAL",
			"displayXPadding": 0,
			"displayYPadding": 0,
			"displayColorCjk": "FF9900",
			"displayColor": "FF9900",
			"displayMaxLineHeight": 1.5,
			"displayCjkSizeRatio": 2,
			"displayOptions": [],
			"displayPadZeros": 0,
			"displayType": "DESTINATION",
			"displayDefaultText": "Not In Service",
			"doorXMultiplier": 0,
			"doorZMultiplier": 0,
			"doorAnimationType": "STANDARD",
			"renderFromOpeningDoorTime": 0,
			"renderUntilOpeningDoorTime": 0,
			"renderFromClosingDoorTime": 0,
			"renderUntilClosingDoorTime": 0,
			"flashOffTime": 0,
			"flashOnTime": 0
		},
		{
			"names": [
				"head_exterior"
			],
			"positionDefinitions": [
				"910436ed"
			],
			"condition": "NORMAL",
			"renderStage": "EXTERIOR",
			"type": "NORMAL",
			"displayXPadding": 0,
			"displayYPadding": 0,
			"displayColorCjk": "FF9900",
			"displayColor": "FF9900",
			"displayMaxLineHeight": 1.5,
			"displayCjkSizeRatio": 2,
			"displayOptions": [],
			"displayPadZeros": 0,
			"displayType": "DESTINATION",
			"displayDefaultText": "Not In Service",
			"doorXMultiplier": 0,
			"doorZMultiplier": 0,
			"doorAnimationType": "STANDARD",
			"renderFromOpeningDoorTime": 0,
			"renderUntilOpeningDoorTime": 0,
			"renderFromClosingDoorTime": 0,
			"renderUntilClosingDoorTime": 0,
			"flashOffTime": 0,
			"flashOnTime": 0
		},
		{
			"names": [
				"head_floor"
			],
			"positionDefinitions": [
				"a4fc036b"
			],
			"condition": "NORMAL",
			"renderStage": "EXTERIOR",
			"type": "FLOOR",
			"displayXPadding": 0,
			"displayYPadding": 0,
			"displayColorCjk": "FF9900",
			"displayColor": "FF9900",
			"displayMaxLineHeight": 1.5,
			"displayCjkSizeRatio": 2,
			"displayOptions": [],
			"displayPadZeros": 0,
			"displayType": "DESTINATION",
			"displayDefaultText": "Not In Service",
			"doorXMultiplier": 0,
			"doorZMultiplier": 0,
			"doorAnimationType": "STANDARD",
			"renderFromOpeningDoorTime": 0,
			"renderUntilOpeningDoorTime": 0,
			"renderFromClosingDoorTime": 0,
			"renderUntilClosingDoorTime": 0,
			"flashOffTime": 0,
			"flashOnTime": 0
		},
		{
			"names": [
				"roof_head_light"
			],
			"positionDefinitions": [
				"40f303e3"
			],
			"condition": "ON_ROUTE_FORWARDS",
			"renderStage": "LIGHT",
			"type": "NORMAL",
			"displayXPadding": 0,
			"displayYPadding": 0,
			"displayColorCjk": "FF9900",
			"displayColor": "FF9900",
			"displayMaxLineHeight": 1.5,
			"displayCjkSizeRatio": 2,
			"displayOptions": [],
			"displayPadZeros": 0,
			"displayType": "DESTINATION",
			"displayDefaultText": "Not In Service",
			"doorXMultiplier": 0,
			"doorZMultiplier": 0,
			"doorAnimationType": "STANDARD",
			"renderFromOpeningDoorTime": 0,
			"renderUntilOpeningDoorTime": 0,
			"renderFromClosingDoorTime": 0,
			"renderUntilClosingDoorTime": 0,
			"flashOffTime": 0,
			"flashOnTime": 0
		},
		{
			"names": [
				"roof_head_light"
			],
			"positionDefinitions": [
				"f7b7d47b"
			],
			"condition": "ON_ROUTE_BACKWARDS",
			"renderStage": "EXTERIOR",
			"type": "NORMAL",
			"displayXPadding": 0,
			"displayYPadding": 0,
			"displayColorCjk": "FF9900",
			"displayColor": "FF9900",
			"displayMaxLineHeight": 1.5,
			"displayCjkSizeRatio": 2,
			"displayOptions": [],
			"displayPadZeros": 0,
			"displayType": "DESTINATION",
			"displayDefaultText": "Not In Service",
			"doorXMultiplier": 0,
			"doorZMultiplier": 0,
			"doorAnimationType": "STANDARD",
			"renderFromOpeningDoorTime": 0,
			"renderUntilOpeningDoorTime": 0,
			"renderFromClosingDoorTime": 0,
			"renderUntilClosingDoorTime": 0,
			"flashOffTime": 0,
			"flashOnTime": 0
		},
		{
			"names": [
				"roof_head_light"
			],
			"positionDefinitions": [
				"29324197"
			],
			"condition": "AT_DEPOT",
			"renderStage": "EXTERIOR",
			"type": "NORMAL",
			"displayXPadding": 0,
			"displayYPadding": 0,
			"displayColorCjk": "FF9900",
			"displayColor": "FF9900",
			"displayMaxLineHeight": 1.5,
			"displayCjkSizeRatio": 2,
			"displayOptions": [],
			"displayPadZeros": 0,
			"displayType": "DESTINATION",
			"displayDefaultText": "Not In Service",
			"doorXMultiplier": 0,
			"doorZMultiplier": 0,
			"doorAnimationType": "STANDARD",
			"renderFromOpeningDoorTime": 0,
			"renderUntilOpeningDoorTime": 0,
			"renderFromClosingDoorTime": 0,
			"renderUntilClosingDoorTime": 0,
			"flashOffTime": 0,
			"flashOnTime": 0
		},
		{
			"names": [
				"head_driver"
			],
			"positionDefinitions": [
				"b3674b22"
			],
			"condition": "ON_ROUTE_FORWARDS",
			"renderStage": "INTERIOR",
			"type": "NORMAL",
			"displayXPadding": 0,
			"displayYPadding": 0,
			"displayColorCjk": "FF9900",
			"displayColor": "FF9900",
			"displayMaxLineHeight": 1.5,
			"displayCjkSizeRatio": 2,
			"displayOptions": [],
			"displayPadZeros": 0,
			"displayType": "DESTINATION",
			"displayDefaultText": "Not In Service",
			"doorXMultiplier": 0,
			"doorZMultiplier": 0,
			"doorAnimationType": "STANDARD",
			"renderFromOpeningDoorTime": 0,
			"renderUntilOpeningDoorTime": 0,
			"renderFromClosingDoorTime": 0,
			"renderUntilClosingDoorTime": 0,
			"flashOffTime": 0,
			"flashOnTime": 0
		},
		{
			"names": [
				"head_driver"
			],
			"positionDefinitions": [
				"20e50983"
			],
			"condition": "ON_ROUTE_BACKWARDS",
			"renderStage": "EXTERIOR",
			"type": "NORMAL",
			"displayXPadding": 0,
			"displayYPadding": 0,
			"displayColorCjk": "FF9900",
			"displayColor": "FF9900",
			"displayMaxLineHeight": 1.5,
			"displayCjkSizeRatio": 2,
			"displayOptions": [],
			"displayPadZeros": 0,
			"displayType": "DESTINATION",
			"displayDefaultText": "Not In Service",
			"doorXMultiplier": 0,
			"doorZMultiplier": 0,
			"doorAnimationType": "STANDARD",
			"renderFromOpeningDoorTime": 0,
			"renderUntilOpeningDoorTime": 0,
			"renderFromClosingDoorTime": 0,
			"renderUntilClosingDoorTime": 0,
			"flashOffTime": 0,
			"flashOnTime": 0
		},
		{
			"names": [
				"head_driver"
			],
			"positionDefinitions": [
				"c9c2b091"
			],
			"condition": "AT_DEPOT",
			"renderStage": "EXTERIOR",
			"type": "NORMAL",
			"displayXPadding": 0,
			"displayYPadding": 0,
			"displayColorCjk": "FF9900",
			"displayColor": "FF9900",
			"displayMaxLineHeight": 1.5,
			"displayCjkSizeRatio": 2,
			"displayOptions": [],
			"displayPadZeros": 0,
			"displayType": "DESTINATION",
			"displayDefaultText": "Not In Service",
			"doorXMultiplier": 0,
			"doorZMultiplier": 0,
			"doorAnimationType": "STANDARD",
			"renderFromOpeningDoorTime": 0,
			"renderUntilOpeningDoorTime": 0,
			"renderFromClosingDoorTime": 0,
			"renderUntilClosingDoorTime": 0,
			"flashOffTime": 0,
			"flashOnTime": 0
		},
		{
			"names": [
				"headlight"
			],
			"positionDefinitions": [
				"b0a25461"
			],
			"condition": "ON_ROUTE_BACKWARDS",
			"renderStage": "ALWAYS_ON_LIGHT",
			"type": "NORMAL",
			"displayXPadding": 0,
			"displayYPadding": 0,
			"displayColorCjk": "FF9900",
			"displayColor": "FF9900",
			"displayMaxLineHeight": 1.5,
			"displayCjkSizeRatio": 2,
			"displayOptions": [],
			"displayPadZeros": 0,
			"displayType": "DESTINATION",
			"displayDefaultText": "Not In Service",
			"doorXMultiplier": 0,
			"doorZMultiplier": 0,
			"doorAnimationType": "STANDARD",
			"renderFromOpeningDoorTime": 0,
			"renderUntilOpeningDoorTime": 0,
			"renderFromClosingDoorTime": 0,
			"renderUntilClosingDoorTime": 0,
			"flashOffTime": 0,
			"flashOnTime": 0
		},
		{
			"names": [
				"taillight"
			],
			"positionDefinitions": [
				"3be8c4f2"
			],
			"condition": "ON_ROUTE_FORWARDS",
			"renderStage": "ALWAYS_ON_LIGHT",
			"type": "NORMAL",
			"displayXPadding": 0,
			"displayYPadding": 0,
			"displayColorCjk": "FF9900",
			"displayColor": "FF9900",
			"displayMaxLineHeight": 1.5,
			"displayCjkSizeRatio": 2,
			"displayOptions": [],
			"displayPadZeros": 0,
			"displayType": "DESTINATION",
			"displayDefaultText": "Not In Service",
			"doorXMultiplier": 0,
			"doorZMultiplier": 0,
			"doorAnimationType": "STANDARD",
			"renderFromOpeningDoorTime": 0,
			"renderUntilOpeningDoorTime": 0,
			"renderFromClosingDoorTime": 0,
			"renderUntilClosingDoorTime": 0,
			"flashOffTime": 0,
			"flashOnTime": 0
		},
		{
			"names": [
				"maskl"
			],
			"positionDefinitions": [
				"6fb2ba62"
			],
			"condition": "ON_ROUTE_BACKWARDS",
			"renderStage": "INTERIOR",
			"type": "NORMAL",
			"displayXPadding": 0,
			"displayYPadding": 0,
			"displayColorCjk": "FF9900",
			"displayColor": "FF9900",
			"displayMaxLineHeight": 1.5,
			"displayCjkSizeRatio": 2,
			"displayOptions": [],
			"displayPadZeros": 0,
			"displayType": "DESTINATION",
			"displayDefaultText": "Not In Service",
			"doorXMultiplier": 0,
			"doorZMultiplier": 0,
			"doorAnimationType": "STANDARD",
			"renderFromOpeningDoorTime": 0,
			"renderUntilOpeningDoorTime": 0,
			"renderFromClosingDoorTime": 0,
			"renderUntilClosingDoorTime": 0,
			"flashOffTime": 0,
			"flashOnTime": 0
		},
		{
			"names": [
				"maskd"
			],
			"positionDefinitions": [
				"1eb2b9fa"
			],
			"condition": "ON_ROUTE_BACKWARDS",
			"renderStage": "INTERIOR",
			"type": "NORMAL",
			"displayXPadding": 0,
			"displayYPadding": 0,
			"displayColorCjk": "FF9900",
			"displayColor": "FF9900",
			"displayMaxLineHeight": 1.5,
			"displayCjkSizeRatio": 2,
			"displayOptions": [],
			"displayPadZeros": 0,
			"displayType": "DESTINATION",
			"displayDefaultText": "Not In Service",
			"doorXMultiplier": 0,
			"doorZMultiplier": 0,
			"doorAnimationType": "STANDARD",
			"renderFromOpeningDoorTime": 0,
			"renderUntilOpeningDoorTime": 0,
			"renderFromClosingDoorTime": 0,
			"renderUntilClosingDoorTime": 0,
			"flashOffTime": 0,
			"flashOnTime": 0
		},
		{
			"names": [
				"maskdr"
			],
			"positionDefinitions": [
				"6b7043e1"
			],
			"condition": "ON_ROUTE_BACKWARDS",
			"renderStage": "EXTERIOR",
			"type": "NORMAL",
			"displayXPadding": 0,
			"displayYPadding": 0,
			"displayColorCjk": "FF9900",
			"displayColor": "FF9900",
			"displayMaxLineHeight": 1.5,
			"displayCjkSizeRatio": 2,
			"displayOptions": [],
			"displayPadZeros": 0,
			"displayType": "DESTINATION",
			"displayDefaultText": "Not In Service",
			"doorXMultiplier": 0,
			"doorZMultiplier": 0,
			"doorAnimationType": "STANDARD",
			"renderFromOpeningDoorTime": 0,
			"renderUntilOpeningDoorTime": 0,
			"renderFromClosingDoorTime": 0,
			"renderUntilClosingDoorTime": 0,
			"flashOffTime": 0,
			"flashOnTime": 0
		},
		{
			"names": [
				"tr1"
			],
			"positionDefinitions": [
				"3428ef07"
			],
			"condition": "ON_ROUTE_FORWARDS",
			"renderStage": "INTERIOR_TRANSLUCENT",
			"type": "NORMAL",
			"displayXPadding": 0,
			"displayYPadding": 0,
			"displayColorCjk": "FF9900",
			"displayColor": "FF9900",
			"displayMaxLineHeight": 1.5,
			"displayCjkSizeRatio": 2,
			"displayOptions": [],
			"displayPadZeros": 0,
			"displayType": "DESTINATION",
			"displayDefaultText": "Not In Service",
			"doorXMultiplier": 0,
			"doorZMultiplier": 0,
			"doorAnimationType": "STANDARD",
			"renderFromOpeningDoorTime": 0,
			"renderUntilOpeningDoorTime": 0,
			"renderFromClosingDoorTime": 0,
			"renderUntilClosingDoorTime": 0,
			"flashOffTime": 0,
			"flashOnTime": 0
		},
		{
			"names": [
				"tr2"
			],
			"positionDefinitions": [
				"ab6990d8"
			],
			"condition": "ON_ROUTE_FORWARDS",
			"renderStage": "INTERIOR_TRANSLUCENT",
			"type": "NORMAL",
			"displayXPadding": 0,
			"displayYPadding": 0,
			"displayColorCjk": "FF9900",
			"displayColor": "FF9900",
			"displayMaxLineHeight": 1.5,
			"displayCjkSizeRatio": 2,
			"displayOptions": [],
			"displayPadZeros": 0,
			"displayType": "DESTINATION",
			"displayDefaultText": "Not In Service",
			"doorXMultiplier": 0,
			"doorZMultiplier": 0,
			"doorAnimationType": "STANDARD",
			"renderFromOpeningDoorTime": 0,
			"renderUntilOpeningDoorTime": 0,
			"renderFromClosingDoorTime": 0,
			"renderUntilClosingDoorTime": 0,
			"flashOffTime": 0,
			"flashOnTime": 0
		},
		{
			"names": [
				"tr1"
			],
			"positionDefinitions": [
				"1d2d0109"
			],
			"condition": "AT_DEPOT",
			"renderStage": "INTERIOR_TRANSLUCENT",
			"type": "NORMAL",
			"displayXPadding": 0,
			"displayYPadding": 0,
			"displayColorCjk": "FF9900",
			"displayColor": "FF9900",
			"displayMaxLineHeight": 1.5,
			"displayCjkSizeRatio": 2,
			"displayOptions": [],
			"displayPadZeros": 0,
			"displayType": "DESTINATION",
			"displayDefaultText": "Not In Service",
			"doorXMultiplier": 0,
			"doorZMultiplier": 0,
			"doorAnimationType": "STANDARD",
			"renderFromOpeningDoorTime": 0,
			"renderUntilOpeningDoorTime": 0,
			"renderFromClosingDoorTime": 0,
			"renderUntilClosingDoorTime": 0,
			"flashOffTime": 0,
			"flashOnTime": 0
		},
		{
			"names": [
				"tr2"
			],
			"positionDefinitions": [
				"f06be89f"
			],
			"condition": "AT_DEPOT",
			"renderStage": "INTERIOR_TRANSLUCENT",
			"type": "NORMAL",
			"displayXPadding": 0,
			"displayYPadding": 0,
			"displayColorCjk": "FF9900",
			"displayColor": "FF9900",
			"displayMaxLineHeight": 1.5,
			"displayCjkSizeRatio": 2,
			"displayOptions": [],
			"displayPadZeros": 0,
			"displayType": "DESTINATION",
			"displayDefaultText": "Not In Service",
			"doorXMultiplier": 0,
			"doorZMultiplier": 0,
			"doorAnimationType": "STANDARD",
			"renderFromOpeningDoorTime": 0,
			"renderUntilOpeningDoorTime": 0,
			"renderFromClosingDoorTime": 0,
			"renderUntilClosingDoorTime": 0,
			"flashOffTime": 0,
			"flashOnTime": 0
		},
		{
			"names": [
				"head_display"
			],
			"positionDefinitions": [
				"236a0f46"
			],
			"condition": "NORMAL",
			"renderStage": "EXTERIOR",
			"type": "DISPLAY",
			"displayXPadding": 0,
			"displayYPadding": 0.6,
			"displayColorCjk": "FF9900",
			"displayColor": "FF9900",
			"displayMaxLineHeight": 1.5,
			"displayCjkSizeRatio": 2,
			"displayOptions": [
				"UPPER_CASE",
				"SPACE_CJK"
			],
			"displayPadZeros": 0,
			"displayType": "DESTINATION",
			"displayDefaultText": "回送|Not In Service",
			"doorXMultiplier": 0,
			"doorZMultiplier": 0,
			"doorAnimationType": "STANDARD",
			"renderFromOpeningDoorTime": 0,
			"renderUntilOpeningDoorTime": 0,
			"renderFromClosingDoorTime": 0,
			"renderUntilClosingDoorTime": 0,
			"flashOffTime": 0,
			"flashOnTime": 0
		},
		{
			"names": [
				"head_display2"
			],
			"positionDefinitions": [
				"98250683"
			],
			"condition": "NORMAL",
			"renderStage": "EXTERIOR",
			"type": "DISPLAY",
			"displayXPadding": 0,
			"displayYPadding": 0.5,
			"displayColorCjk": "FF0000",
			"displayColor": "FF0000",
			"displayMaxLineHeight": 1.5,
			"displayCjkSizeRatio": 2,
			"displayOptions": [
				"UPPER_CASE"
			],
			"displayPadZeros": 0,
			"displayType": "ROUTE_NUMBER",
			"displayDefaultText": "",
			"doorXMultiplier": 0,
			"doorZMultiplier": 0,
			"doorAnimationType": "STANDARD",
			"renderFromOpeningDoorTime": 0,
			"renderUntilOpeningDoorTime": 0,
			"renderFromClosingDoorTime": 0,
			"renderUntilClosingDoorTime": 0,
			"flashOffTime": 0,
			"flashOnTime": 0
		},
		{
			"names": [
				"head_index"
			],
			"positionDefinitions": [
				"990017e"
			],
			"condition": "NORMAL",
			"renderStage": "EXTERIOR",
			"type": "DISPLAY",
			"displayXPadding": 0,
			"displayYPadding": 0,
			"displayColorCjk": "FF9900",
			"displayColor": "FF9900",
			"displayMaxLineHeight": 1.5,
			"displayCjkSizeRatio": 2,
			"displayOptions": [],
			"displayPadZeros": 3,
			"displayType": "DEPARTURE_INDEX",
			"displayDefaultText": "",
			"doorXMultiplier": 0,
			"doorZMultiplier": 0,
			"doorAnimationType": "STANDARD",
			"renderFromOpeningDoorTime": 0,
			"renderUntilOpeningDoorTime": 0,
			"renderFromClosingDoorTime": 0,
			"renderUntilClosingDoorTime": 0,
			"flashOffTime": 0,
			"flashOnTime": 0
		}
	],
	"modelYOffset": 1,
	"gangwayInnerSideResource": "",
	"gangwayInnerTopResource": "",
	"gangwayInnerBottomResource": "",
	"gangwayOuterSideResource": "",
	"gangwayOuterTopResource": "",
	"gangwayOuterBottomResource": "",
	"gangwayWidth": 1.5,
	"gangwayHeight": 2.25,
	"gangwayYOffset": 1,
	"gangwayZOffset": 0.5,
	"barrierInnerSideResource": "",
	"barrierInnerTopResource": "",
	"barrierInnerBottomResource": "",
	"barrierOuterSideResource": "",
	"barrierOuterTopResource": "",
	"barrierOuterBottomResource": "",
	"barrierWidth": 2.25,
	"barrierHeight": 1,
	"barrierYOffset": 1.25,
	"barrierZOffset": 0.25
}